depsize/__init__.py
depsize/depsize.py
depsize-0.1.8.dist-info/METADATA
depsize-0.1.8.dist-info/WHEEL
depsize-0.1.8.dist-info/entry_points.txt
depsize-0.1.8.dist-info/licenses/LICENSE
depsize-0.1.8.dist-info/RECORD
