Metadata-Version: 2.4
Name: depsize
Version: 0.1.8
Summary: A package that tells you the size of your dependencies in Megabytes!
Project-URL: Homepage, https://github.com/tobiasmcvey/depsize
License: MIT License
License-File: LICENSE
Keywords: dependencies,python
Requires-Python: >=3.8
